asn_nmap/__init__.py
asn_nmap/asn.py
asn_nmap/export.py
asn_nmap/nmap.py
asn_nmap-0.1.9.dist-info/METADATA
asn_nmap-0.1.9.dist-info/WHEEL
asn_nmap-0.1.9.dist-info/top_level.txt
asn_nmap-0.1.9.dist-info/RECORD
